{
  "e13585c1bbc23c440db580ed3d0362dd": [
    "2.0.0f6",
    "2.0.2f2"
  ],
  "c838052a240cb84f4f6e2439f5bbdc53": [
    "2.5.1f4",
    "2.5.1f5",
    "2.6.0f7",
    "2.6.1f3"
  ],
  "bd3e65b436ca9bddcf08b9369dc166c9": [
    "3.1.0f3",
    "3.1.0f4"
  ],
  "66fcee7a9b922f2ff5b0d9b52d46547c": [
    "3.2.0f4",
    "3.3.0f4"
  ],
  "0be713b9a525f321879cf7985e5cb6a0": [
    "3.4.0f5",
    "3.4.1f5",
    "3.4.2f2",
    "3.4.2f3"
  ],
  "64eff32a9399a62c0c1ff38ffc206094": [
    "3.5.0b7",
    "3.5.0f1",
    "3.5.0f5",
    "3.5.1f2",
    "3.5.2f2",
    "3.5.3f3",
    "3.5.4f1",
    "3.5.5f2",
    "3.5.5f3",
    "3.5.6f4",
    "3.5.7f6"
  ],
  "34f82447344517eacb2e4f407ad31706": [
    "4.0.0f7",
    "4.0.1f2",
    "4.1.0f4",
    "4.1.1f4",
    "4.1.2f1",
    "4.1.3f3",
    "4.1.5f1",
    "4.2.0f4",
    "4.2.1f4",
    "4.2.2f1"
  ],
  "fb0635f60817266fc2448281f0e1bf8e": [
    "4.3.0b3"
  ],
  "cd299f8158c5d24d299bc2279a86222d": [
    "4.3.0f4",
    "4.3.1f1",
    "4.3.2f1",
    "4.3.3f1",
    "4.3.4f1",
    "4.3.7p2",
    "4.5.0f6",
    "4.5.1f3",
    "4.5.2f1",
    "4.5.3f3",
    "4.5.4f1",
    "4.5.5f1",
    "4.6.0f3"
  ]
}