{
  "a7729bb8d7394740adc071c820e356d9": [
    "2.0.0"
  ],
  "314d92333aa5a47ee10d7468c3eaf762": [
    "2.0.2",
    "2.1.0",
    "2.5.1"
  ],
  "696274ce5463dacc7067eb983ee36abb": [
    "2.6.0",
    "2.6.1"
  ],
  "be015150eb4131c5679550a87b2db5a0": [
    "3.1.0",
    "3.2.0",
    "3.3.0",
    "3.4.0",
    "3.4.1",
    "3.4.2",
    "3.5.0",
    "3.5.1",
    "3.5.2",
    "3.5.3",
    "3.5.4",
    "3.5.5",
    "3.5.6",
    "3.5.7",
    "4.0.0",
    "4.0.1",
    "4.1.0",
    "4.1.1",
    "4.1.2",
    "4.1.3",
    "4.1.5",
    "4.2.0",
    "4.2.1",
    "4.2.2"
  ],
  "474aacecd95040b09cf12989eb350382": [
    "4.3.0"
  ],
  "26942566836e59b29434b0f484ec3308": [
    "4.3.0",
    "4.3.1",
    "4.3.2",
    "4.3.3",
    "4.3.4",
    "4.3.7",
    "4.5.0",
    "4.5.1",
    "4.5.2",
    "4.5.3",
    "4.5.4",
    "4.6.0"
  ]
}