{
  "version": 2,
  "is_array": false,
  "size": -1,
  "index": 0,
  "meta_flag": 32768,
  "name": "Base",
  "type": "MonoManager",
  "children": [
    {
      "version": 1,
      "is_array": false,
      "size": -1,
      "index": 1,
      "meta_flag": 0,
      "name": "m_Scripts",
      "type": "set",
      "children": [
        {
          "version": 1,
          "is_array": true,
          "size": -1,
          "index": 2,
          "meta_flag": 0,
          "name": "Array",
          "type": "Array",
          "children": [
            {
              "version": 1,
              "is_array": false,
              "size": 4,
              "index": 3,
              "meta_flag": 0,
              "name": "size",
              "type": "int",
              "children": []
            },
            {
              "version": 1,
              "is_array": false,
              "size": 12,
              "index": 4,
              "meta_flag": 0,
              "name": "data",
              "type": "PPtr<MonoScript>",
              "children": [
                {
                  "version": 1,
                  "is_array": false,
                  "size": 4,
                  "index": 5,
                  "meta_flag": 1,
                  "name": "m_FileID",
                  "type": "int",
                  "children": []
                },
                {
                  "version": 1,
                  "is_array": false,
                  "size": 8,
                  "index": 6,
                  "meta_flag": 1,
                  "name": "m_PathID",
                  "type": "SInt64",
                  "children": []
                }
              ]
            }
          ]
        }
      ]
    },
    {
      "version": 1,
      "is_array": false,
      "size": -1,
      "index": 7,
      "meta_flag": 32768,
      "name": "m_AssemblyNames",
      "type": "vector",
      "children": [
        {
          "version": 1,
          "is_array": true,
          "size": -1,
          "index": 8,
          "meta_flag": 32768,
          "name": "Array",
          "type": "Array",
          "children": [
            {
              "version": 1,
              "is_array": false,
              "size": 4,
              "index": 9,
              "meta_flag": 0,
              "name": "size",
              "type": "int",
              "children": []
            },
            {
              "version": 1,
              "is_array": false,
              "size": -1,
              "index": 10,
              "meta_flag": 32768,
              "name": "data",
              "type": "string",
              "children": [
                {
                  "version": 1,
                  "is_array": true,
                  "size": -1,
                  "index": 11,
                  "meta_flag": 16385,
                  "name": "Array",
                  "type": "Array",
                  "children": [
                    {
                      "version": 1,
                      "is_array": false,
                      "size": 4,
                      "index": 12,
                      "meta_flag": 1,
                      "name": "size",
                      "type": "int",
                      "children": []
                    },
                    {
                      "version": 1,
                      "is_array": false,
                      "size": 1,
                      "index": 13,
                      "meta_flag": 1,
                      "name": "data",
                      "type": "char",
                      "children": []
                    }
                  ]
                }
              ]
            }
          ]
        }
      ]
    }
  ]
}